{
  "task_id": "medium_replacement_delay",
  "id": "medium_replacement_delay",
  "has_grader": true,
  "difficulty": "medium",
  "title": "Replacement for VIP shipment error",
  "grader": "graders.medium_replacement_delay:grade",
  "grader_name": "grade_medium_replacement_delay",
  "grader_module": "graders.medium_replacement_delay",
  "grader_function": "grade",
  "constraints": [
    "Route shipping and warehouse issues to fulfillment.",
    "Use urgent priority when the failure blocks an imminent event.",
    "Reply should promise overnight replacement and confirm no return is needed first."
  ]
}
